murf/__init__.py
murf/auth/__init__.py
murf/auth/client.py
murf/base_client.py
murf/client.py
murf/core/__init__.py
murf/core/api_error.py
murf/core/client_wrapper.py
murf/core/datetime_utils.py
murf/core/file.py
murf/core/http_client.py
murf/core/jsonable_encoder.py
murf/core/pydantic_utilities.py
murf/core/query_encoder.py
murf/core/remove_none_from_dict.py
murf/core/request_options.py
murf/core/serialization.py
murf/core/unchecked_base_model.py
murf/dubbing/__init__.py
murf/dubbing/client.py
murf/dubbing/jobs/__init__.py
murf/dubbing/jobs/client.py
murf/dubbing/jobs/types/__init__.py
murf/dubbing/jobs/types/jobs_create_request_priority.py
murf/dubbing/jobs/types/jobs_create_with_project_id_request_priority.py
murf/dubbing/languages/__init__.py
murf/dubbing/languages/client.py
murf/dubbing/projects/__init__.py
murf/dubbing/projects/client.py
murf/dubbing/projects/types/__init__.py
murf/dubbing/projects/types/api_create_project_request_dubbing_type.py
murf/dubbing_client.py
murf/environment.py
murf/errors/__init__.py
murf/errors/bad_request_error.py
murf/errors/forbidden_error.py
murf/errors/internal_server_error.py
murf/errors/payment_required_error.py
murf/errors/service_unavailable_error.py
murf/errors/unauthorized_error.py
murf/py.typed
murf/region.py
murf/stream_input/__init__.py
murf/stream_input/types/__init__.py
murf/stream_input/types/receive_message.py
murf/stream_input/types/send_message.py
murf/stream_input/types/text_to_speech_model.py
murf/text/__init__.py
murf/text/client.py
murf/text_to_speech/__init__.py
murf/text_to_speech/client.py
murf/types/__init__.py
murf/types/api_job_response.py
murf/types/api_job_response_dubbing_type.py
murf/types/api_job_response_priority.py
murf/types/api_project_response.py
murf/types/api_project_response_dubbing_type.py
murf/types/api_voice.py
murf/types/api_voice_gender.py
murf/types/audio_output.py
murf/types/auth_token_response.py
murf/types/character_count.py
murf/types/clear_context.py
murf-2.2.5.dist-info/LICENSE
murf-2.2.5.dist-info/METADATA
murf-2.2.5.dist-info/WHEEL
murf-2.2.5.dist-info/RECORD
